fix_pyorch/__init__.py
fix_pyorch/message.py
fix_pyorch/message_spec.py
fix_pyorch-1.0.3.dist-info/LICENSE
fix_pyorch-1.0.3.dist-info/METADATA
fix_pyorch-1.0.3.dist-info/WHEEL
fix_pyorch-1.0.3.dist-info/top_level.txt
fix_pyorch-1.0.3.dist-info/RECORD
