Metadata-Version: 2.1
Name: fix-pyorch
Version: 1.0.3
Summary: A library to parse FIX formatted files, using FIXOrchestra metadata
Home-page: https://github.com/fincloud-io/fix_pyorch
Author: Jon Jenkins
Author-email: jj@fincloud.io
Classifier: Programming Language :: Python :: 3
Classifier: License :: OSI Approved :: Apache Software License
Classifier: Operating System :: OS Independent
Requires-Python: >=3.6
License-File: LICENSE
